evoproc_procedures/__init__.py
evoproc_procedures/builders.py
evoproc_procedures/helpers.py
evoproc_procedures/models.py
evoproc_procedures/ollama.py
evoproc_procedures/pipelines.py
evoproc_procedures/prompts.py
evoproc_procedures/repairs.py
evoproc_procedures/runners.py
evoproc_procedures/schemas.py
evoproc_procedures/examples/notebook_demo.ipynb
evoproc_procedures-1.0.0.dist-info/METADATA
evoproc_procedures-1.0.0.dist-info/WHEEL
evoproc_procedures-1.0.0.dist-info/top_level.txt
evoproc_procedures-1.0.0.dist-info/RECORD
