Metadata-Version: 2.4
Name: evoproc-procedures
Version: 1.0.0
Summary: Domain procedures, schemas, prompts, runners, and backends for EvoProc
Author: Malia Barker
License: MIT
Project-URL: Homepage, https://github.com/<you>/<repo>
Project-URL: Documentation, https://<your-docs-site>
Project-URL: Source, https://github.com/<you>/<repo>
Project-URL: Issues, https://github.com/<you>/<repo>/issues
Requires-Python: >=3.10
Requires-Dist: pydantic>=2
Requires-Dist: jsonschema>=4
Requires-Dist: evoproc>=0.1.0
Provides-Extra: llm
Requires-Dist: ollama>=0.2; extra == "llm"
Requires-Dist: httpx>=0.24; extra == "llm"
Provides-Extra: dev
Requires-Dist: pytest>=7; extra == "dev"
Requires-Dist: ruff; extra == "dev"
Requires-Dist: mypy; extra == "dev"
